SPyQR
