Metadata-Version: 2.1
Name: SPyQR
Version: 1.0.0
Summary: A bad python package for bad Romans
Home-page: https://github.com/lukekh/SPyQR
Author: lukekh
Author-email: groupython@gmail.com
License: UNKNOWN
Platform: UNKNOWN
Classifier: Programming Language :: Python :: 3
Classifier: License :: OSI Approved :: MIT License
Classifier: Operating System :: OS Independent
Requires-Python: >=3.0
